x_mcp/__init__.py
x_mcp/server.py
x_mcp-0.1.0.dist-info/METADATA
x_mcp-0.1.0.dist-info/WHEEL
x_mcp-0.1.0.dist-info/entry_points.txt
x_mcp-0.1.0.dist-info/licenses/LICENSE
x_mcp-0.1.0.dist-info/RECORD
