Metadata-Version: 2.3
Name: x-mcp
Version: 0.1.0
Summary: A server to create drafts of X(twitter) posts, threads using LLMs and post directly from the chat.
Author-email: Vidhu Panhavoor Vasudevan <vidhuvasudevan.2000@gmail.com>
Requires-Python: >=3.12
Requires-Dist: httpx>=0.28.0
Requires-Dist: mcp>=1.1.0
Requires-Dist: python-dotenv>=1.0.1
Requires-Dist: tweepy>=4.14.0
